<?xml version="1.0" encoding="utf-8"?>
<!DOCTYPE hibernate-mapping PUBLIC "-//Hibernate/Hibernate Mapping DTD 3.0//EN"
"http://hibernate.sourceforge.net/hibernate-mapping-3.0.dtd">
<!-- 
    Mapping file autogenerated by MyEclipse Persistence Tools
-->
<hibernate-mapping>
    <class name="uml.hotel.model.UmlCustomer" table="uml_customer" catalog="uml">
        <id name="cid" type="java.lang.Integer">
            <column name="cID" />
            <generator class="identity" />
        </id>
        <property name="cusName" type="java.lang.String">
            <column name="cusName" length="50" />
        </property>
        <property name="cusPhone" type="java.lang.String">
            <column name="cusPhone" length="15" />
        </property>
        <property name="cusId" type="java.lang.String">
            <column name="cusID" length="18" />
        </property>
        <property name="sex" type="java.lang.String">
            <column name="sex" length="5" />
        </property>
        <property name="cusPwd" type="java.lang.String">
            <column name="cusPwd" length="8" />
        </property>
        <property name="statusId" type="java.lang.Integer">
            <column name="statusID" />
        </property>
        <property name="vipId" type="java.lang.Integer">
            <column name="vipID" />
        </property>
    </class>
</hibernate-mapping>
